LICENSE
MANIFEST.in
README.rst
setup.py
test/test_simple.py
test/test_usury.py
test/test_util.py
usury/__init__.py
usury/simple.py
usury/util.py
usury.egg-info/PKG-INFO
usury.egg-info/SOURCES.txt
usury.egg-info/dependency_links.txt
usury.egg-info/top_level.txt