Metadata-Version: 1.1
Name: usury
Version: 0.1.0
Summary: Python interest calculation library
Home-page: https://github.com/rtdean/usury
Author: Ryan T. Dean
Author-email: rtdean@cytherianage.net
License: Apache 2.0
Keywords: usury interest
Platform: UNKNOWN
Classifier: Development Status :: 2 - Pre-Alpha
Classifier: Intended Audience :: Developers
Classifier: License :: OSI Approved :: Apache Software License
Classifier: Programming Language :: Python
Classifier: Topic :: Office/Business :: Financial
Classifier: Topic :: Software Development :: Libraries :: Python Modules
